{
  "cli": {
    "version": ">= 18.4.0",
    "appVersionSource": "remote"
  },
  "build": {
    "development": {
      "developmentClient": true,
      "distribution": "internal"
    },
    "preview": {
      "distribution": "internal",
      "env": {
        "EXPO_PUBLIC_API_URL": "https://api-production-8227.up.railway.app"
      }
    },
    "production": {
      "autoIncrement": true,
      "env": {
        "EXPO_PUBLIC_API_URL": "https://api-production-8227.up.railway.app",
        "YARN_ENABLE_IMMUTABLE_INSTALLS": "false"
      }
    },
    "apk": {
      "android": {
        "buildType": "apk"
      },
      "env": {
        "EXPO_PUBLIC_API_URL": "https://api-production-8227.up.railway.app",
        "YARN_ENABLE_IMMUTABLE_INSTALLS": "false"
      }
    }
  },
  "submit": {
    "production": {}
  }
}
